setup.py
simple_format/__init__.py
simple_format/_parse.py
simple_format/_render.py
simple_format/_scan.py
simple_format.egg-info/PKG-INFO
simple_format.egg-info/SOURCES.txt
simple_format.egg-info/dependency_links.txt
simple_format.egg-info/top_level.txt