Metadata-Version: 1.1
Name: simple-format
Version: 0.2
Summary: A simple text formatter converting a readable plain text to html
Home-page: https://github.com/sherwoodwang/simple-format
Author: Sherwood Wang
Author-email: sherwood@wang.onl
License: UNKNOWN
Platform: UNKNOWN
Classifier: Programming Language :: Python
